{
  "parent": "minecraft:recipes/root",
  "criteria": {
    "has_ingot_titanium": {
      "conditions": {
        "items": [
          {
            "items": [
              "hbmntm:ingot_titanium"
            ]
          }
        ]
      },
      "trigger": "minecraft:inventory_changed"
    },
    "has_the_recipe": {
      "conditions": {
        "recipe": "hbmntm:stamp_titanium_flat_from_nether_brick"
      },
      "trigger": "minecraft:recipe_unlocked"
    }
  },
  "requirements": [
    [
      "has_ingot_titanium",
      "has_the_recipe"
    ]
  ],
  "rewards": {
    "recipes": [
      "hbmntm:stamp_titanium_flat_from_nether_brick"
    ]
  },
  "sends_telemetry_event": false
}